fuck_game/__init__.py
fuck_game/game_level.py
fuck_game/game_ui.py
fuck_game/main.py
fuck_game-0.0.10.dist-info/METADATA
fuck_game-0.0.10.dist-info/WHEEL
fuck_game-0.0.10.dist-info/entry_points.txt
fuck_game-0.0.10.dist-info/top_level.txt
fuck_game-0.0.10.dist-info/RECORD
