Metadata-Version: 2.1
Name: fuck-game
Version: 0.0.10
Summary: Brain teaser game, made with python & curses. Play in the terminal. For Linux, Mac OS and Windows.
Author: 4sushi
License: MIT
Project-URL: Homepage, https://github.com/4sushi/fuck-game
Keywords: game,brain-teaser,curses
Classifier: Programming Language :: Python :: 3
Classifier: License :: OSI Approved :: MIT License
Classifier: Operating System :: OS Independent
Requires-Python: >=3.7
Requires-Dist: windows-curses >=2.3.2 ; platform_system == "Windows"
